elphick/pandera_utils/__init__.py
elphick/pandera_utils/pandera_utils.py
elphick/pandera_utils/utils/__init__.py
elphick/pandera_utils/utils/pandera_io_pandas_io.py
elphick/pandera_utils/utils/pandera_schema_statistics_pandas.py
pandera_utils-0.2.1.dist-info/LICENSE
pandera_utils-0.2.1.dist-info/METADATA
pandera_utils-0.2.1.dist-info/WHEEL
pandera_utils-0.2.1.dist-info/RECORD
